anndict/__init__.py
anndict/adata_dict/__init__.py
anndict/adata_dict/adata_dict.py
anndict/adata_dict/adata_dict_fapply.py
anndict/adata_dict/adata_dict_utils.py
anndict/adata_dict/add_stratification.py
anndict/adata_dict/build.py
anndict/adata_dict/concatenate.py
anndict/adata_dict/dict_utils.py
anndict/adata_dict/read.py
anndict/adata_dict/utils.py
anndict/adata_dict/write.py
anndict/annotate/__init__.py
anndict/annotate/cells/__init__.py
anndict/annotate/cells/benchmarking/__init__.py
anndict/annotate/cells/benchmarking/agreement_metrics.py
anndict/annotate/cells/benchmarking/ai_compare_cell_type_labels.py
anndict/annotate/cells/benchmarking/label_utils.py
anndict/annotate/cells/de_novo/__init__.py
anndict/annotate/cells/de_novo/annotate_biological_process.py
anndict/annotate/cells/de_novo/annotate_cell_subtype.py
anndict/annotate/cells/de_novo/annotate_cell_subtype_by_comparison.py
anndict/annotate/cells/de_novo/annotate_cell_type.py
anndict/annotate/cells/de_novo/annotate_cell_type_by_comparison.py
anndict/annotate/cells/de_novo/annotate_from_expected_cell_types.py
anndict/annotate/cells/de_novo/automated_clustering.py
anndict/annotate/cells/de_novo/base.py
anndict/annotate/cells/de_novo/cell_type_score.py
anndict/annotate/cells/label_transfer/__init__.py
anndict/annotate/cells/label_transfer/adata_predicoder.py
anndict/annotate/cells/label_transfer/harmony.py
anndict/annotate/cells/label_transfer/predicoder.py
anndict/annotate/cells/label_transfer/sklearn_classifier.py
anndict/annotate/genes/__init__.py
anndict/annotate/genes/make_cell_type_gene_list.py
anndict/automated_label_management/__init__.py
anndict/automated_label_management/unify_columns_between_adata.py
anndict/automated_label_management/unify_columns_within_adata.py
anndict/automated_label_management/clean_single_column/__init__.py
anndict/automated_label_management/clean_single_column/in_adata_obs.py
anndict/automated_label_management/clean_single_column/in_adata_var.py
anndict/llm/__init__.py
anndict-0.3.69.dist-info/licenses/LICENSE
anndict-0.3.69.dist-info/METADATA
anndict-0.3.69.dist-info/WHEEL
anndict-0.3.69.dist-info/top_level.txt
anndict-0.3.69.dist-info/RECORD
