Metadata-Version: 2.4
Name: anndict
Version: 0.3.69
Summary: Conveniently process a dictionary of anndatas (adata_dict)
Author: ggit12
License: BSD-3-Clause
Project-URL: Source, https://github.com/ggit12/anndictionary
Project-URL: Documentation, https://ggit12.github.io/anndictionary
Classifier: Development Status :: 3 - Alpha
Classifier: Intended Audience :: Developers
Classifier: License :: OSI Approved :: BSD License
Classifier: Programming Language :: Python :: 3
Classifier: Programming Language :: Python :: 3.7
License-File: LICENSE
Requires-Dist: numpy==1.26.4
Requires-Dist: pandas==2.2.2
Requires-Dist: scikit-learn==1.5.1
Requires-Dist: scanpy==1.10.2
Requires-Dist: anndata==0.10.8
Requires-Dist: IPython==8.26.0
Requires-Dist: scipy==1.14.1
Requires-Dist: seaborn==0.13.2
Requires-Dist: matplotlib==3.9.2
Requires-Dist: harmonypy==0.0.10
Requires-Dist: langchain==0.2.14
Requires-Dist: langchain-community==0.2.12
Requires-Dist: langchain-openai==0.1.22
Requires-Dist: langchain-anthropic==0.1.23
Requires-Dist: langchain-google-genai==1.0.10
Requires-Dist: langchain-aws==0.1.17
Requires-Dist: boto3==1.34.162
Requires-Dist: bokeh==3.4.3
Requires-Dist: holoviews==1.19.1
Requires-Dist: krippendorff==0.7.0
Dynamic: license-file
